simplemdm_sdk/__init__.py
simplemdm_sdk/_connection.py
simplemdm_sdk/_simplemdm.py
simplemdm_sdk/_rest_api_endpoints/__init__.py
simplemdm_sdk/_rest_api_endpoints/account.py
simplemdm_sdk/_rest_api_endpoints/apps.py
simplemdm_sdk/_rest_api_endpoints/assignment_groups.py
simplemdm_sdk/_rest_api_endpoints/custom_attributes.py
simplemdm_sdk/_rest_api_endpoints/custom_configuration_profiles.py
simplemdm_sdk/_rest_api_endpoints/dep_servers.py
simplemdm_sdk/_rest_api_endpoints/device_groups.py
simplemdm_sdk/_rest_api_endpoints/devices.py
simplemdm_sdk/_rest_api_endpoints/enrollments.py
simplemdm_sdk/_rest_api_endpoints/installed_apps.py
simplemdm_sdk/_rest_api_endpoints/logs.py
simplemdm_sdk/_rest_api_endpoints/lost_mode.py
simplemdm_sdk/_rest_api_endpoints/managed_app_configs.py
simplemdm_sdk/_rest_api_endpoints/profiles.py
simplemdm_sdk/_rest_api_endpoints/push_certificate.py
simplemdm_sdk/_rest_api_endpoints/script_jobs.py
simplemdm_sdk/_rest_api_endpoints/scripts.py
simplemdm_sdk/_rest_api_endpoints/models/__init__.py
simplemdm_sdk/_rest_api_endpoints/models/_base_model.py
simplemdm_sdk/_rest_api_endpoints/models/accounts.py
simplemdm_sdk/_rest_api_endpoints/models/apps.py
simplemdm_sdk/_rest_api_endpoints/models/assignment_groups.py
simplemdm_sdk/_rest_api_endpoints/models/custom_attributes.py
simplemdm_sdk/_rest_api_endpoints/models/custom_configuration_profiles.py
simplemdm_sdk/_rest_api_endpoints/models/dep_servers.py
simplemdm_sdk/_rest_api_endpoints/models/device_groups.py
simplemdm_sdk/_rest_api_endpoints/models/devices.py
simplemdm_sdk/_rest_api_endpoints/models/enrollments.py
simplemdm_sdk/_rest_api_endpoints/models/installed_apps.py
simplemdm_sdk/_rest_api_endpoints/models/logs.py
simplemdm_sdk/_rest_api_endpoints/models/managed_app_configs.py
simplemdm_sdk/_rest_api_endpoints/models/profiles.py
simplemdm_sdk/_rest_api_endpoints/models/push_certificate.py
simplemdm_sdk/_rest_api_endpoints/models/script_jobs.py
simplemdm_sdk-0.1.0.dist-info/licenses/LICENSE.txt
simplemdm_sdk-0.1.0.dist-info/METADATA
simplemdm_sdk-0.1.0.dist-info/WHEEL
simplemdm_sdk-0.1.0.dist-info/top_level.txt
simplemdm_sdk-0.1.0.dist-info/RECORD
