Metadata-Version: 2.4
Name: simplemdm_sdk
Version: 0.1.0
Summary: Highly opinionated SimpleMDM Python library
Home-page: https://github.com/ripeda/SimpleMDM-SDK-Python
Author: RIPEDA Consulting
Author-email: info@ripeda.com
License: BSD 3-Clause License
Requires-Python: >=3.6
License-File: LICENSE.txt
Requires-Dist: requests
Requires-Dist: pydantic
Dynamic: author
Dynamic: author-email
Dynamic: description
Dynamic: description-content-type
Dynamic: home-page
Dynamic: license
Dynamic: license-file
Dynamic: requires-dist
Dynamic: requires-python
Dynamic: summary
